foxinternalclient/__init__.py
foxinternalclient/api_client.py
foxinternalclient/api_response.py
foxinternalclient/configuration.py
foxinternalclient/exceptions.py
foxinternalclient/py.typed
foxinternalclient/rest.py
foxinternalclient/api/__init__.py
foxinternalclient/api/device_api.py
foxinternalclient/api/fox_factory_api.py
foxinternalclient/api/gitlab_api.py
foxinternalclient/api/internal_api.py
foxinternalclient/api/paste_api.py
foxinternalclient/api/release_api.py
foxinternalclient/api/stats_api.py
foxinternalclient/models/__init__.py
foxinternalclient/models/body_change_password_profile_change_password_post.py
foxinternalclient/models/build_status_enum.py
foxinternalclient/models/build_task_response.py
foxinternalclient/models/build_task_short_response.py
foxinternalclient/models/device_internal_response.py
foxinternalclient/models/device_response.py
foxinternalclient/models/device_stats_response.py
foxinternalclient/models/device_update_body.py
foxinternalclient/models/ff_status_enum.py
foxinternalclient/models/ff_status_response.py
foxinternalclient/models/global_stats_aggregation_model.py
foxinternalclient/models/http_validation_error.py
foxinternalclient/models/list_response_build_task_short_response.py
foxinternalclient/models/list_response_release_response.py
foxinternalclient/models/list_response_short_device_response.py
foxinternalclient/models/list_response_short_release_response.py
foxinternalclient/models/list_response_str.py
foxinternalclient/models/list_response_user_short_response.py
foxinternalclient/models/log_list_response.py
foxinternalclient/models/log_response.py
foxinternalclient/models/maintainer_short_model.py
foxinternalclient/models/new_build_task_body.py
foxinternalclient/models/new_device_body.py
foxinternalclient/models/paste_input.py
foxinternalclient/models/paste_output.py
foxinternalclient/models/recovery_img_response.py
foxinternalclient/models/release_groups_response.py
foxinternalclient/models/release_internal_response.py
foxinternalclient-5.3.0.dist-info/METADATA
foxinternalclient-5.3.0.dist-info/WHEEL
foxinternalclient-5.3.0.dist-info/top_level.txt
foxinternalclient-5.3.0.dist-info/RECORD
